appclis/__init__.py
appclis/chen.py
appclis/chief.py
appclis/settings/__init__.py
appclis/settings/chen_settings.py
appclis/settings/settings_manager.py
libagentic/__init__.py
libagentic/agents.py
libagentic/models.py
libagentic/mongo.py
libagentic/prompts.py
libagentic/providers.py
libagentic/tools/__init__.py
libagentic/tools/search.py
libagentic/tools/time.py
libchatinterface/__init__.py
libchatinterface/cli.py
libchatinterface/costs.py
libchatinterface/session.py
libshared/__init__.py
libshared/mongo.py
chief_ai-0.1.6.dist-info/METADATA
chief_ai-0.1.6.dist-info/WHEEL
chief_ai-0.1.6.dist-info/entry_points.txt
chief_ai-0.1.6.dist-info/licenses/LICENSE
chief_ai-0.1.6.dist-info/RECORD
