Metadata-Version: 2.4
Name: chief-ai
Version: 0.1.6
Summary: AI agent framework with Chief and Chen, a conversational AI psychologist with web search and multi-provider support in your terminal.
Project-URL: Homepage, https://github.com/tistaharahap/chief-ai
Project-URL: Repository, https://github.com/tistaharahap/chief-ai
Project-URL: Issues, https://github.com/tistaharahap/chief-ai/issues
Author-email: Batista Harahap <batista@bango29.com>
License: MIT
License-File: LICENSE
Keywords: agent,ai,anthropic,assistant,chat,openai,openrouter,psychologist
Classifier: Development Status :: 4 - Beta
Classifier: Intended Audience :: Developers
Classifier: License :: OSI Approved :: MIT License
Classifier: Programming Language :: Python :: 3
Classifier: Programming Language :: Python :: 3.13
Classifier: Topic :: Communications :: Chat
Classifier: Topic :: Scientific/Engineering :: Artificial Intelligence
Classifier: Topic :: Software Development :: Libraries :: Python Modules
Requires-Python: >=3.13
Requires-Dist: asyncer>=0.0.8
Requires-Dist: beanie>=2.0.0
Requires-Dist: coolname>=2.2.0
Requires-Dist: logfire>=4.4.0
Requires-Dist: pydantic-ai>=1.0.1
Requires-Dist: pydantic-graph>=1.0.1
Requires-Dist: pydantic-settings>=2.10.1
Requires-Dist: python-dotenv>=1.1.1
Requires-Dist: tavily-python>=0.7.11
Requires-Dist: tiktoken>=0.11.0
Requires-Dist: typer>=0.17.4
Requires-Dist: typing-extensions>=4.0.0; python_version < '3.11'
Requires-Dist: uuid7>=0.1.0
Requires-Dist: uvicorn>=0.35.0
